Workbook

Sheet Debt Payoff Calculator
A1: Creditor | B1: Monthly Payment ($) | C1: Balance ($)
A2: MORTGAGE | B2: 1970 | C2: 267000
A3: SOLAR | B3: 500
A4: Cc
A17: Monthly | B17: =SUM(B2:B16) -> 2470
A18: Balance | C18: =SUM(C2:C16) -> 267000

Sheet Loan Calculator
A1: Loan Amount ($) | B1: Loan Term (Years) | C1: Interest Rate (%) | D1: Principal & Interest Payment ($) | E1: Escrow Payment ($) | F1: Total Payment ($) | G1: MONTHLY SAVINGS ($) | H1: Early Payoff (Years) | I1: Total Interest Saved ($) | J1: Effective Interest Rate (Adjusted %)
A2: 267000 | B2: 30 | C2: 7 | D2: =IF(AND(ISNUMBER(A2), ISNUMBER(B2), ISNUMBER(C2)), ROUND(PMT(C2/1200, B2*12, -A2), 2), "") -> 1776.36 | E2: 435 | F2: =IF(AND(ISNUMBER(D2), ISNUMBER(E2)), D2 + E2, "") -> 2211.36 | G2: ='Summary Chart'!B8 -> 258.64 | H2: =IF(AND(ISNUMBER(A2), ISNUMBER(C2), ISNUMBER(D2), ISNUMBER(G2), G2>0), ROUND(NPER(C2/1200, -(D2+G2), A2)/12, 1), "") -> 20.8 | I2: =IF(AND(ISNUMBER(D2), ISNUMBER(B2), ISNUMBER(H2), ISNUMBER(G2), G2>0), ROUND((D2*B2*12 - A2) - ((D2+G2)*H2*12 - A2), 2), "") -> 131553.6 | J2: =IF(AND(ISNUMBER(D2), ISNUMBER(B2), ISNUMBER(A2), ISNUMBER(C2), ISNUMBER(I2), I2>0), ROUND(C2 - ((I2 / (D2*B2*12 - A2)) * C2), 3), "") -> 4.528

Sheet Summary Chart
A1: Interest Type | B1: Amount
A2: Original Interest | B2: ='Loan Calculator'!D2*'Loan Calculator'!B2*12 - 'Loan Calculator'!A2 -> 372489.6
A3: Interest Saved | B3: ='Loan Calculator'!I2 -> 131553.6
A4: New Interest | B4: =B2-B3 -> 240936
A6: Old Monthly Payments (Debts) | B6: ='Debt Payoff Calculator'!B17 -> 2470
A7: New Monthly Mortgage Payment | B7: ='Loan Calculator'!F2 -> 2211.36
A8: Monthly Savings | B8: =B6-B7 -> 258.64
A9: Adjusted Effective Interest Rate (%) | B9: ='Loan Calculator'!J2 -> 4.528
A10: Loan Pays Off In (Years) | B10: ='Loan Calculator'!H2 -> 20.8

Sheet Debt Summary
A1: 30 YEAR 3/1 ARM | B1: COMPLETE BENEFITS OVERVIEW - (ROUGH DRAFT) | C1: (NO PRE-PAYMENT PENALTY)
A2: Loan Term (Years) | C2: ='Loan Calculator'!B2 -> 30
A3: Interest Rate (%) | C3: ='Loan Calculator'!C2 -> 7
A4: New Total Monthly Payment | C4: ='Summary Chart'!B7 -> 2211.36
A5: DEBTS & MORTGAGES INCLUDED:
A6: CREDITOR | B6: BALANCE | C6: PAYMENT
A7: ROCKET MORTGAGE | B7: 247784 | C7: 1970
A9: Totals | B9: =SUM(B7:B8) -> 247784 | C9: =SUM(C7:C8) -> 1970
A10: MONYHLY PAYMENT OVERVIEW:
A11: Current Total Monthly Payments | B11: (+) | C11: ='Summary Chart'!B6 -> 2470
A12: New Total Monthly Payment | B12: (-) | C12: ='Summary Chart'!B7 -> 2211.36
A13: Monthly Savings | B13: (=) | C13: ='Summary Chart'!B8 -> 258.64
A14: IF SAVINGS APPLIED BACK TO LOAN:
A15: Net Effective Interest Rate (%) | C15: ='Summary Chart'!B9 -> 4.528
A16: Loan Pays Off In (Years) | C16: ='Summary Chart'!B10 -> 20.8
A17: Additional Interest savings | C17: ='Summary Chart'!B3 -> 131553.6
A18: END RESULT:
A19: 2 SKIPPED PAYMENTS | B19: P | C19: =C11*2 -> 4940
A20: ESCROW RESERVE REFUND | C20: 2000
A21: Total Accumulated Cash to you upon completion | C21: =SUM(C19:C20) -> 6940
